topotem/__init__.py
topotem/dummy_data.py
topotem/fft_mapping.py
topotem/lattice_structure_tools.py
topotem/polarisation.py
topotem-0.1.2.dist-info/LICENSE
topotem-0.1.2.dist-info/METADATA
topotem-0.1.2.dist-info/WHEEL
topotem-0.1.2.dist-info/RECORD
